{
  "eufemiaVersion": "11.2.1",
  "extractedAt": "2026-05-08T09:15:03.637Z",
  "themes": [
    "ui",
    "sbanken",
    "eiendom",
    "carnegie"
  ],
  "counts": {
    "primitiveTokens": 80,
    "icons": 286,
    "components": 141,
    "themes": {
      "ui": {
        "scale": 430,
        "semantic": 206,
        "semanticDark": 206
      },
      "sbanken": {
        "scale": 553,
        "semantic": 206,
        "semanticDark": 206
      },
      "eiendom": {
        "scale": 440,
        "semantic": 0,
        "semanticDark": 0
      },
      "carnegie": {
        "scale": 433,
        "semantic": 206,
        "semanticDark": 0
      }
    }
  }
}